Metadata-Version: 1.1
Name: tktextext
Version: 1.0
Summary: Extensions for tkinter.Text (provides read-only, scrollbars, line numbers etc)
Home-page: https://bitbucket.org/aivarannamaa/tktextext
Author: UNKNOWN
Author-email: UNKNOWN
License: MIT
Keywords: tk tkinter Text
Platform: UNKNOWN
Classifier: Development Status :: 5 - Production/Stable
Classifier: Intended Audience :: Developers
Classifier: License :: Freeware
Classifier: License :: OSI Approved :: MIT License
Classifier: Natural Language :: English
Classifier: Programming Language :: Python
Classifier: Programming Language :: Python :: 2
Classifier: Programming Language :: Python :: 3
Classifier: Topic :: Software Development
Classifier: Topic :: Software Development :: Libraries
